jamo/__init__.py
jamo/jamo.py
jamo/data/U+11xx.json
jamo/data/U+31xx.json
jamo-0.4.1.dist-info/DESCRIPTION.rst
jamo-0.4.1.dist-info/METADATA
jamo-0.4.1.dist-info/RECORD
jamo-0.4.1.dist-info/WHEEL
jamo-0.4.1.dist-info/metadata.json
jamo-0.4.1.dist-info/top_level.txt
