Metadata-Version: 1.1
Name: jamo
Version: 0.4.1
Summary: A Hangul syllable and jamo analyzer.
Home-page: https://github.com/jdongian/python-jamo
Author: Joshua Dong
Author-email: jdong42@gmail.com
License: http://www.apache.org/licenses/LICENSE-2.0
Keywords: Korean Hangul jamo syllable nlp
Platform: UNKNOWN
Classifier: License :: OSI Approved :: Apache Software License
Classifier: Programming Language :: Python :: 3
Classifier: Programming Language :: Python :: 3.2
Classifier: Programming Language :: Python :: 3.3
Classifier: Programming Language :: Python :: 3.4
